drbutil/__init__.py
drbutil/__version__.py
drbutil/io.py
drbutil/util.py
drbutil-0.0.22.dist-info/LICENCE
drbutil-0.0.22.dist-info/METADATA
drbutil-0.0.22.dist-info/WHEEL
drbutil-0.0.22.dist-info/top_level.txt
drbutil-0.0.22.dist-info/RECORD
