Metadata-Version: 2.1
Name: drbutil
Version: 0.0.22
Summary: A tiny collection of geometry processing routines frequently used in my projects.
Author-email: "Dennis R. Bukenberger" <dennis.bukenberger@tum.de>
Project-URL: Homepage, https://github.com/dbukenberger/drbutil
Classifier: Programming Language :: Python :: 3
Classifier: License :: OSI Approved :: MIT License
Classifier: Operating System :: OS Independent
Requires-Python: >=3.8
License-File: LICENCE
